Metadata-Version: 2.1
Name: transformers-cfg
Version: 0.2.7
Summary: Extension of Transformers library for Context-Free Grammar Constrained Decoding with EBNF grammars
Home-page: https://github.com/epfl-dlab/transformers-CFG
Author: EPFL-dlab
Author-email: saibo.geng@epfl.ch
License: UNKNOWN
Platform: UNKNOWN
Classifier: Programming Language :: Python :: 3
Classifier: License :: OSI Approved :: MIT License
Classifier: Operating System :: OS Independent
License-File: LICENSE
Requires-Dist: torch>=2.0.0
Requires-Dist: numpy>=1.24.2
Requires-Dist: transformers>=4.37.2
Requires-Dist: tokenizers>=0.19.0
Requires-Dist: termcolor>=2.4.0
Requires-Dist: sentencepiece>=0.1.99
Requires-Dist: protobuf>=4.25.2
Requires-Dist: setuptools>=69.0.3
Provides-Extra: dev
Requires-Dist: pre-commit; extra == "dev"
Requires-Dist: pytest; extra == "dev"
Requires-Dist: twine; extra == "dev"
